subsurfer/__init__.py
subsurfer/__main__.py
subsurfer/subsurfer.py
subsurfer/core/__init__.py
subsurfer/core/cli/__init__.py
subsurfer/core/cli/cli.py
subsurfer/core/cli/parser.py
subsurfer/core/config/__init__.py
subsurfer/core/config/config.yaml
subsurfer/core/controller/__init__.py
subsurfer/core/controller/controller.py
subsurfer/core/handler/__init__.py
subsurfer/core/handler/active_handler.py
subsurfer/core/handler/passive_handler.py
subsurfer/core/handler/active/srv.py
subsurfer/core/handler/active/sweep.py
subsurfer/core/handler/active/zone.py
subsurfer/core/handler/passive/abuseipdb.py
subsurfer/core/handler/passive/alienvault.py
subsurfer/core/handler/passive/anubisdb.py
subsurfer/core/handler/passive/bufferover.py
subsurfer/core/handler/passive/crtsh.py
subsurfer/core/handler/passive/digitorus.py
subsurfer/core/handler/passive/dnsarchive.py
subsurfer/core/handler/passive/freecampdev.py
subsurfer/core/handler/passive/hackertarget.py
subsurfer/core/handler/passive/myssl.py
subsurfer/core/handler/passive/shrewdeye.py
subsurfer/core/handler/passive/subdomaincenter.py
subsurfer/core/handler/passive/subdomainfinder.py
subsurfer/core/handler/passive/urlscan.py
subsurfer/core/handler/passive/webarchive.py
subsurfer/core/handler/web/web_scanner.py
subsurfer/core/utils/version_checker.py
subsurfer-0.3.1.dist-info/licenses/LICENSE
subsurfer-0.3.1.dist-info/METADATA
subsurfer-0.3.1.dist-info/WHEEL
subsurfer-0.3.1.dist-info/entry_points.txt
subsurfer-0.3.1.dist-info/top_level.txt
subsurfer-0.3.1.dist-info/RECORD
