Metadata-Version: 2.4
Name: subsurfer
Version: 0.3.1
Summary: Red Teaming and Web Bug Bounty Fast Asset Identification Tool
Home-page: https://github.com/arrester/subsurfer
Author: arrester
Author-email: arresterloyal@gmail.com
Project-URL: Bug Reports, https://github.com/arrester/subsurfer/issues
Project-URL: Source, https://github.com/arrester/subsurfer
Project-URL: Documentation, https://github.com/arrester/subsurfer#readme
Keywords: security,subdomain enumeration,bug bounty,red team,web security
Classifier: Development Status :: 3 - Alpha
Classifier: Intended Audience :: Information Technology
Classifier: Intended Audience :: System Administrators
Classifier: Topic :: Security
Classifier: Topic :: Internet :: WWW/HTTP
Classifier: License :: OSI Approved :: MIT License
Classifier: Programming Language :: Python :: 3
Classifier: Programming Language :: Python :: 3.13
Classifier: Operating System :: OS Independent
Requires-Python: >=3.9
License-File: LICENSE
Requires-Dist: rich>=13.7.0
Requires-Dist: aiohttp>=3.9.1
Requires-Dist: beautifulsoup4>=4.12.2
Requires-Dist: dnspython>=2.4.2
Requires-Dist: pyyaml>=6.0.1
Requires-Dist: asyncio>=3.4.3
Requires-Dist: pytest>=7.4.3
Requires-Dist: pytest-asyncio>=0.23.2
Requires-Dist: python-Wappalyzer>=0.3.1
Requires-Dist: setuptools>=75.6.0
Dynamic: author
Dynamic: author-email
Dynamic: classifier
Dynamic: description
Dynamic: description-content-type
Dynamic: home-page
Dynamic: keywords
Dynamic: license-file
Dynamic: project-url
Dynamic: requires-dist
Dynamic: requires-python
Dynamic: summary
